namebase_exchange/__init__.py
namebase_exchange/enums.py
namebase_exchange/exchange.py
namebase_exchange/utils.py
namebase_exchange/websocket_data.py
namebase_exchange-0.0.8.dist-info/LICENSE
namebase_exchange-0.0.8.dist-info/METADATA
namebase_exchange-0.0.8.dist-info/WHEEL
namebase_exchange-0.0.8.dist-info/top_level.txt
namebase_exchange-0.0.8.dist-info/RECORD
