Metadata-Version: 2.1
Name: namebase-exchange
Version: 0.0.8
Summary: Python Client to interact with the Namebase Exchange API
Home-page: https://github.com/wy/namebase-exchange-python
Author: Wing Chan
Author-email: wingyungchan@gmail.com
License: UNKNOWN
Platform: UNKNOWN
Classifier: Programming Language :: Python :: 3
Classifier: Programming Language :: Python :: 3.6
Classifier: Programming Language :: Python :: 3.7
Classifier: License :: OSI Approved :: MIT License
Classifier: Operating System :: OS Independent
Classifier: Intended Audience :: Developers
Classifier: Topic :: Software Development :: Libraries :: Python Modules
Classifier: Natural Language :: English
Requires-Python: >=3.6
Requires-Dist: requests
